{
    "no_relation": "none",
    "/business/company/founders": "founders",
    "/people/person/place_of_birth": "birthplace",
    "/people/deceased_person/place_of_death": "death",
    "/business/company_shareholder/major_shareholder_of": "shareholder",
    "/people/ethnicity/people": "people",
    "/location/neighborhood/neighborhood_of": "neighborhood",
    "/sports/sports_team/location": "location",
    "/business/company/industry": "industry",
    "/business/company/place_founded": "founded",
    "/location/administrative_division/country": "country",
    "/sports/sports_team_location/teams": "teams",
    "/people/person/nationality": "nationality",
    "/people/person/religion": "religion",
    "/business/company/advisors": "advisor",
    "/people/person/ethnicity": "ethnicity",
    "/people/ethnicity/geographic_distribution": "distribution",
    "/business/person/company":"company",
    "/business/company/major_shareholders": "shareholders",
    "/people/person/place_lived": "lived",
    "/people/person/profession": "profession",
    "/location/country/capital": "capital",
    "/location/location/contains": "contains",
    "/location/country/administrative_divisions": "divisions",
    "/people/person/children": "children"
}